{
  "1": {
    "level": 1,
    "nextExp": 5,
    "totalExp": 0
  },
  "2": {
    "level": 2,
    "nextExp": 11,
    "totalExp": 5
  },
  "3": {
    "level": 3,
    "nextExp": 20,
    "totalExp": 16
  },
  "4": {
    "level": 4,
    "nextExp": 31,
    "totalExp": 36
  },
  "5": {
    "level": 5,
    "nextExp": 45,
    "totalExp": 67
  },
  "6": {
    "level": 6,
    "nextExp": 61,
    "totalExp": 112
  },
  "7": {
    "level": 7,
    "nextExp": 80,
    "totalExp": 173
  },
  "8": {
    "level": 8,
    "nextExp": 101,
    "totalExp": 253
  },
  "9": {
    "level": 9,
    "nextExp": 125,
    "totalExp": 354
  },
  "10": {
    "level": 10,
    "nextExp": 151,
    "totalExp": 479
  },
  "11": {
    "level": 11,
    "nextExp": 180,
    "totalExp": 630
  },
  "12": {
    "level": 12,
    "nextExp": 211,
    "totalExp": 810
  },
  "13": {
    "level": 13,
    "nextExp": 245,
    "totalExp": 1021
  },
  "14": {
    "level": 14,
    "nextExp": 281,
    "totalExp": 1266
  },
  "15": {
    "level": 15,
    "nextExp": 320,
    "totalExp": 1547
  },
  "16": {
    "level": 16,
    "nextExp": 361,
    "totalExp": 1867
  },
  "17": {
    "level": 17,
    "nextExp": 405,
    "totalExp": 2228
  },
  "18": {
    "level": 18,
    "nextExp": 451,
    "totalExp": 2633
  },
  "19": {
    "level": 19,
    "nextExp": 500,
    "totalExp": 3084
  },
  "20": {
    "level": 20,
    "nextExp": 551,
    "totalExp": 3584
  },
  "21": {
    "level": 21,
    "nextExp": 605,
    "totalExp": 4135
  },
  "22": {
    "level": 22,
    "nextExp": 661,
    "totalExp": 4740
  },
  "23": {
    "level": 23,
    "nextExp": 720,
    "totalExp": 5401
  },
  "24": {
    "level": 24,
    "nextExp": 781,
    "totalExp": 6121
  },
  "25": {
    "level": 25,
    "nextExp": 845,
    "totalExp": 6902
  },
  "26": {
    "level": 26,
    "nextExp": 911,
    "totalExp": 7747
  },
  "27": {
    "level": 27,
    "nextExp": 980,
    "totalExp": 8658
  },
  "28": {
    "level": 28,
    "nextExp": 1051,
    "totalExp": 9638
  },
  "29": {
    "level": 29,
    "nextExp": 1125,
    "totalExp": 10689
  },
  "30": {
    "level": 30,
    "nextExp": 1219,
    "totalExp": 11814
  },
  "31": {
    "level": 31,
    "nextExp": 1499,
    "totalExp": 13033
  },
  "32": {
    "level": 32,
    "nextExp": 1967,
    "totalExp": 14532
  },
  "33": {
    "level": 33,
    "nextExp": 2621,
    "totalExp": 16499
  },
  "34": {
    "level": 34,
    "nextExp": 3463,
    "totalExp": 19120
  },
  "35": {
    "level": 35,
    "nextExp": 4492,
    "totalExp": 22583
  },
  "36": {
    "level": 36,
    "nextExp": 5708,
    "totalExp": 27075
  },
  "37": {
    "level": 37,
    "nextExp": 7110,
    "totalExp": 32783
  },
  "38": {
    "level": 38,
    "nextExp": 8700,
    "totalExp": 39893
  },
  "39": {
    "level": 39,
    "nextExp": 10477,
    "totalExp": 48593
  },
  "40": {
    "level": 40,
    "nextExp": 10696,
    "totalExp": 59070
  },
  "41": {
    "level": 41,
    "nextExp": 11352,
    "totalExp": 69766
  },
  "42": {
    "level": 42,
    "nextExp": 12447,
    "totalExp": 81118
  },
  "43": {
    "level": 43,
    "nextExp": 13978,
    "totalExp": 93565
  },
  "44": {
    "level": 44,
    "nextExp": 15948,
    "totalExp": 107543
  },
  "45": {
    "level": 45,
    "nextExp": 18355,
    "totalExp": 123491
  },
  "46": {
    "level": 46,
    "nextExp": 21200,
    "totalExp": 141846
  },
  "47": {
    "level": 47,
    "nextExp": 24483,
    "totalExp": 163046
  },
  "48": {
    "level": 48,
    "nextExp": 28203,
    "totalExp": 187529
  },
  "49": {
    "level": 49,
    "nextExp": 32361,
    "totalExp": 215732
  },
  "50": {
    "level": 50,
    "nextExp": 36957,
    "totalExp": 248093
  },
  "51": {
    "level": 51,
    "nextExp": 41990,
    "totalExp": 285050
  },
  "52": {
    "level": 52,
    "nextExp": 47461,
    "totalExp": 327040
  },
  "53": {
    "level": 53,
    "nextExp": 53370,
    "totalExp": 374501
  },
  "54": {
    "level": 54,
    "nextExp": 59716,
    "totalExp": 427871
  },
  "55": {
    "level": 55,
    "nextExp": 66500,
    "totalExp": 487587
  },
  "56": {
    "level": 56,
    "nextExp": 73722,
    "totalExp": 554087
  },
  "57": {
    "level": 57,
    "nextExp": 81382,
    "totalExp": 627809
  },
  "58": {
    "level": 58,
    "nextExp": 89479,
    "totalExp": 709191
  },
  "59": {
    "level": 59,
    "nextExp": 98014,
    "totalExp": 798670
  },
  "60": {
    "level": 60,
    "nextExp": 106986,
    "totalExp": 896684
  }
}
