{
"storeId": 53,
"storeName": "月光群舞<br>イベントアイテム交換所",
"storeBanner": "Masquerade2310_title",
"sortWeight": 700,
"startAt": null,
"endAt": "2023-11-30 14:00:00",
"storePrefabAddress": "",
"confirmWindowAddress": "",
"conditions": null,
"products": [
{
"productId": 221592,
"storeId": 53,
"sortWeight": 1000,
"exchangeLimit": 5,
"startAt": null,
"endAt": "2023-11-30 14:00:00",
"resetType": 0,
"resetDetail": null,
"product": {
"rewardType": 3,
"objectId": 10,
"objectValue": 1
},
"currency": {
"currencyType": 3,
"objectId": 190,
"objectValue": 1000
},
"condition": []
},
{
"productId": 221593,
"storeId": 53,
"sortWeight": 1000,
"exchangeLimit": 20,
"startAt": null,
"endAt": "2023-11-30 14:00:00",
"resetType": 0,
"resetDetail": null,
"product": {
"rewardType": 3,
"objectId": 135,
"objectValue": 1
},
"currency": {
"currencyType": 3,
"objectId": 190,
"objectValue": 1500
},
"condition": []
},
{
"productId": 221594,
"storeId": 53,
"sortWeight": 1000,
"exchangeLimit": 3,
"startAt": null,
"endAt": "2023-11-30 14:00:00",
"resetType": 0,
"resetDetail": null,
"product": {
"rewardType": 3,
"objectId": 29,
"objectValue": 1
},
"currency": {
"currencyType": 3,
"objectId": 190,
"objectValue": 4000
},
"condition": []
},
{
"productId": 221595,
"storeId": 53,
"sortWeight": 1000,
"exchangeLimit": 10,
"startAt": null,
"endAt": "2023-11-30 14:00:00",
"resetType": 0,
"resetDetail": null,
"product": {
"rewardType": 3,
"objectId": 28,
"objectValue": 1
},
"currency": {
"currencyType": 3,
"objectId": 190,
"objectValue": 800
},
"condition": []
},
{
"productId": 221596,
"storeId": 53,
"sortWeight": 1000,
"exchangeLimit": 10,
"startAt": null,
"endAt": "2023-11-30 14:00:00",
"resetType": 0,
"resetDetail": null,
"product": {
"rewardType": 3,
"objectId": 27,
"objectValue": 1
},
"currency": {
"currencyType": 3,
"objectId": 190,
"objectValue": 160
},
"condition": []
},
{
"productId": 221597,
"storeId": 53,
"sortWeight": 1000,
"exchangeLimit": 1,
"startAt": null,
"endAt": "2023-11-30 14:00:00",
"resetType": 0,
"resetDetail": null,
"product": {
"rewardType": 3,
"objectId": 191,
"objectValue": 1
},
"currency": {
"currencyType": 3,
"objectId": 190,
"objectValue": 400
},
"condition": []
},
{
"productId": 221598,
"storeId": 53,
"sortWeight": 1000,
"exchangeLimit": 1,
"startAt": null,
"endAt": "2023-11-30 14:00:00",
"resetType": 0,
"resetDetail": null,
"product": {
"rewardType": 3,
"objectId": 193,
"objectValue": 1
},
"currency": {
"currencyType": 3,
"objectId": 190,
"objectValue": 400
},
"condition": []
},
{
"productId": 221599,
"storeId": 53,
"sortWeight": 1000,
"exchangeLimit": 1,
"startAt": null,
"endAt": "2023-11-30 14:00:00",
"resetType": 0,
"resetDetail": null,
"product": {
"rewardType": 3,
"objectId": 194,
"objectValue": 1
},
"currency": {
"currencyType": 3,
"objectId": 190,
"objectValue": 400
},
"condition": []
},
{
"productId": 221600,
"storeId": 53,
"sortWeight": 1000,
"exchangeLimit": 2,
"startAt": null,
"endAt": "2023-11-30 14:00:00",
"resetType": 0,
"resetDetail": null,
"product": {
"rewardType": 3,
"objectId": 79,
"objectValue": 5
},
"currency": {
"currencyType": 3,
"objectId": 190,
"objectValue": 2500
},
"condition": []
},
{
"productId": 221601,
"storeId": 53,
"sortWeight": 1000,
"exchangeLimit": 20,
"startAt": null,
"endAt": "2023-11-30 14:00:00",
"resetType": 0,
"resetDetail": null,
"product": {
"rewardType": 3,
"objectId": 78,
"objectValue": 5
},
"currency": {
"currencyType": 3,
"objectId": 190,
"objectValue": 65
},
"condition": []
},
{
"productId": 221602,
"storeId": 53,
"sortWeight": 1000,
"exchangeLimit": 30,
"startAt": null,
"endAt": "2023-11-30 14:00:00",
"resetType": 0,
"resetDetail": null,
"product": {
"rewardType": 3,
"objectId": 59,
"objectValue": 10
},
"currency": {
"currencyType": 3,
"objectId": 190,
"objectValue": 1000
},
"condition": []
},
{
"productId": 221603,
"storeId": 53,
"sortWeight": 1000,
"exchangeLimit": 500,
"startAt": null,
"endAt": "2023-11-30 14:00:00",
"resetType": 0,
"resetDetail": null,
"product": {
"rewardType": 3,
"objectId": 11,
"objectValue": 1000
},
"currency": {
"currencyType": 3,
"objectId": 190,
"objectValue": 40
},
"condition": []
},
{
"productId": 221604,
"storeId": 53,
"sortWeight": 1000,
"exchangeLimit": 250,
"startAt": null,
"endAt": "2023-11-30 14:00:00",
"resetType": 0,
"resetDetail": null,
"product": {
"rewardType": 3,
"objectId": 30,
"objectValue": 1000
},
"currency": {
"currencyType": 3,
"objectId": 190,
"objectValue": 40
},
"condition": []
},
{
"productId": 221605,
"storeId": 53,
"sortWeight": 1000,
"exchangeLimit": 600,
"startAt": null,
"endAt": "2023-11-30 14:00:00",
"resetType": 0,
"resetDetail": null,
"product": {
"rewardType": 3,
"objectId": 35,
"objectValue": 500
},
"currency": {
"currencyType": 3,
"objectId": 190,
"objectValue": 20
},
"condition": []
},
{
"productId": 221606,
"storeId": 53,
"sortWeight": 1000,
"exchangeLimit": 30,
"startAt": null,
"endAt": "2023-11-30 14:00:00",
"resetType": 0,
"resetDetail": null,
"product": {
"rewardType": 3,
"objectId": 15,
"objectValue": 1
},
"currency": {
"currencyType": 3,
"objectId": 190,
"objectValue": 40
},
"condition": []
},
{
"productId": 221607,
"storeId": 53,
"sortWeight": 1000,
"exchangeLimit": 15,
"startAt": null,
"endAt": "2023-11-30 14:00:00",
"resetType": 0,
"resetDetail": null,
"product": {
"rewardType": 3,
"objectId": 16,
"objectValue": 1
},
"currency": {
"currencyType": 3,
"objectId": 190,
"objectValue": 80
},
"condition": []
},
{
"productId": 221608,
"storeId": 53,
"sortWeight": 1000,
"exchangeLimit": 5,
"startAt": null,
"endAt": "2023-11-30 14:00:00",
"resetType": 0,
"resetDetail": null,
"product": {
"rewardType": 3,
"objectId": 17,
"objectValue": 1
},
"currency": {
"currencyType": 3,
"objectId": 190,
"objectValue": 160
},
"condition": []
},
{
"productId": 221609,
"storeId": 53,
"sortWeight": 1000,
"exchangeLimit": 30,
"startAt": null,
"endAt": "2023-11-30 14:00:00",
"resetType": 0,
"resetDetail": null,
"product": {
"rewardType": 3,
"objectId": 21,
"objectValue": 1
},
"currency": {
"currencyType": 3,
"objectId": 190,
"objectValue": 40
},
"condition": []
},
{
"productId": 221610,
"storeId": 53,
"sortWeight": 1000,
"exchangeLimit": 15,
"startAt": null,
"endAt": "2023-11-30 14:00:00",
"resetType": 0,
"resetDetail": null,
"product": {
"rewardType": 3,
"objectId": 22,
"objectValue": 1
},
"currency": {
"currencyType": 3,
"objectId": 190,
"objectValue": 80
},
"condition": []
},
{
"productId": 221611,
"storeId": 53,
"sortWeight": 1000,
"exchangeLimit": 5,
"startAt": null,
"endAt": "2023-11-30 14:00:00",
"resetType": 0,
"resetDetail": null,
"product": {
"rewardType": 3,
"objectId": 23,
"objectValue": 1
},
"currency": {
"currencyType": 3,
"objectId": 190,
"objectValue": 160
},
"condition": []
},
{
"productId": 221612,
"storeId": 53,
"sortWeight": 1000,
"exchangeLimit": 30,
"startAt": null,
"endAt": "2023-11-30 14:00:00",
"resetType": 0,
"resetDetail": null,
"product": {
"rewardType": 3,
"objectId": 24,
"objectValue": 1
},
"currency": {
"currencyType": 3,
"objectId": 190,
"objectValue": 40
},
"condition": []
},
{
"productId": 221613,
"storeId": 53,
"sortWeight": 1000,
"exchangeLimit": 15,
"startAt": null,
"endAt": "2023-11-30 14:00:00",
"resetType": 0,
"resetDetail": null,
"product": {
"rewardType": 3,
"objectId": 25,
"objectValue": 1
},
"currency": {
"currencyType": 3,
"objectId": 190,
"objectValue": 80
},
"condition": []
},
{
"productId": 221614,
"storeId": 53,
"sortWeight": 1000,
"exchangeLimit": 5,
"startAt": null,
"endAt": "2023-11-30 14:00:00",
"resetType": 0,
"resetDetail": null,
"product": {
"rewardType": 3,
"objectId": 26,
"objectValue": 1
},
"currency": {
"currencyType": 3,
"objectId": 190,
"objectValue": 160
},
"condition": []
},
{
"productId": 221615,
"storeId": 53,
"sortWeight": 1000,
"exchangeLimit": 40,
"startAt": null,
"endAt": "2023-11-30 14:00:00",
"resetType": 0,
"resetDetail": null,
"product": {
"rewardType": 3,
"objectId": 53,
"objectValue": 1
},
"currency": {
"currencyType": 3,
"objectId": 190,
"objectValue": 100
},
"condition": []
},
{
"productId": 221616,
"storeId": 53,
"sortWeight": 1000,
"exchangeLimit": 0,
"startAt": null,
"endAt": "2023-11-30 14:00:00",
"resetType": 0,
"resetDetail": null,
"product": {
"rewardType": 3,
"objectId": 35,
"objectValue": 5
},
"currency": {
"currencyType": 3,
"objectId": 190,
"objectValue": 1
},
"condition": []
}
],
"characters": []
}