{
"storeId": 63,
"storeName": "星海往くクルーズトレイン<br>イベントアイテム交換所",
"storeBanner": "TrainRevival2405_title",
"sortWeight": 0,
"startAt": null,
"endAt": "2024-06-06 14:00:00",
"storePrefabAddress": "",
"confirmWindowAddress": "",
"conditions": null,
"products": [
{
"productId": 221831,
"storeId": 63,
"sortWeight": 1000,
"exchangeLimit": 3,
"startAt": null,
"endAt": "2024-06-06 14:00:00",
"resetType": 0,
"resetDetail": null,
"product": {
"rewardType": 3,
"objectId": 10,
"objectValue": 1
},
"currency": {
"currencyType": 3,
"objectId": 172,
"objectValue": 1000
},
"condition": []
},
{
"productId": 221832,
"storeId": 63,
"sortWeight": 1000,
"exchangeLimit": 15,
"startAt": null,
"endAt": "2024-06-06 14:00:00",
"resetType": 0,
"resetDetail": null,
"product": {
"rewardType": 3,
"objectId": 135,
"objectValue": 1
},
"currency": {
"currencyType": 3,
"objectId": 172,
"objectValue": 1500
},
"condition": []
},
{
"productId": 221833,
"storeId": 63,
"sortWeight": 1000,
"exchangeLimit": 2,
"startAt": null,
"endAt": "2024-06-06 14:00:00",
"resetType": 0,
"resetDetail": null,
"product": {
"rewardType": 3,
"objectId": 29,
"objectValue": 1
},
"currency": {
"currencyType": 3,
"objectId": 172,
"objectValue": 4000
},
"condition": []
},
{
"productId": 221834,
"storeId": 63,
"sortWeight": 1000,
"exchangeLimit": 10,
"startAt": null,
"endAt": "2024-06-06 14:00:00",
"resetType": 0,
"resetDetail": null,
"product": {
"rewardType": 3,
"objectId": 28,
"objectValue": 1
},
"currency": {
"currencyType": 3,
"objectId": 172,
"objectValue": 800
},
"condition": []
},
{
"productId": 221835,
"storeId": 63,
"sortWeight": 1000,
"exchangeLimit": 10,
"startAt": null,
"endAt": "2024-06-06 14:00:00",
"resetType": 0,
"resetDetail": null,
"product": {
"rewardType": 3,
"objectId": 27,
"objectValue": 1
},
"currency": {
"currencyType": 3,
"objectId": 172,
"objectValue": 160
},
"condition": []
},
{
"productId": 221836,
"storeId": 63,
"sortWeight": 1000,
"exchangeLimit": 1,
"startAt": null,
"endAt": "2024-06-06 14:00:00",
"resetType": 0,
"resetDetail": null,
"product": {
"rewardType": 3,
"objectId": 11072201,
"objectValue": 1
},
"currency": {
"currencyType": 3,
"objectId": 172,
"objectValue": 600
},
"condition": []
},
{
"productId": 221837,
"storeId": 63,
"sortWeight": 1000,
"exchangeLimit": 1,
"startAt": null,
"endAt": "2024-06-06 14:00:00",
"resetType": 0,
"resetDetail": null,
"product": {
"rewardType": 3,
"objectId": 11151101,
"objectValue": 1
},
"currency": {
"currencyType": 3,
"objectId": 172,
"objectValue": 600
},
"condition": []
},
{
"productId": 221838,
"storeId": 63,
"sortWeight": 1000,
"exchangeLimit": 1,
"startAt": null,
"endAt": "2024-06-06 14:00:00",
"resetType": 0,
"resetDetail": null,
"product": {
"rewardType": 3,
"objectId": 11152101,
"objectValue": 1
},
"currency": {
"currencyType": 3,
"objectId": 172,
"objectValue": 600
},
"condition": []
},
{
"productId": 221839,
"storeId": 63,
"sortWeight": 1000,
"exchangeLimit": 1,
"startAt": null,
"endAt": "2024-06-06 14:00:00",
"resetType": 0,
"resetDetail": null,
"product": {
"rewardType": 3,
"objectId": 173,
"objectValue": 1
},
"currency": {
"currencyType": 3,
"objectId": 172,
"objectValue": 400
},
"condition": [
{
"class": "AggregateHavingItemOnExchangeLimit",
"itemId": 173,
"stockId": 0,
"cardType": 0,
"officeLv": 0,
"officeProductId": 0,
"isAscendingOrder": true,
"relationProductIds": []
}
]
},
{
"productId": 221840,
"storeId": 63,
"sortWeight": 1000,
"exchangeLimit": 1,
"startAt": null,
"endAt": "2024-06-06 14:00:00",
"resetType": 0,
"resetDetail": null,
"product": {
"rewardType": 3,
"objectId": 174,
"objectValue": 1
},
"currency": {
"currencyType": 3,
"objectId": 172,
"objectValue": 400
},
"condition": [
{
"class": "AggregateHavingItemOnExchangeLimit",
"itemId": 174,
"stockId": 0,
"cardType": 0,
"officeLv": 0,
"officeProductId": 0,
"isAscendingOrder": true,
"relationProductIds": []
}
]
},
{
"productId": 221841,
"storeId": 63,
"sortWeight": 1000,
"exchangeLimit": 1,
"startAt": null,
"endAt": "2024-06-06 14:00:00",
"resetType": 0,
"resetDetail": null,
"product": {
"rewardType": 3,
"objectId": 175,
"objectValue": 1
},
"currency": {
"currencyType": 3,
"objectId": 172,
"objectValue": 400
},
"condition": [
{
"class": "AggregateHavingItemOnExchangeLimit",
"itemId": 175,
"stockId": 0,
"cardType": 0,
"officeLv": 0,
"officeProductId": 0,
"isAscendingOrder": true,
"relationProductIds": []
}
]
},
{
"productId": 221842,
"storeId": 63,
"sortWeight": 1000,
"exchangeLimit": 1,
"startAt": null,
"endAt": "2024-06-06 14:00:00",
"resetType": 0,
"resetDetail": null,
"product": {
"rewardType": 3,
"objectId": 176,
"objectValue": 1
},
"currency": {
"currencyType": 3,
"objectId": 172,
"objectValue": 400
},
"condition": [
{
"class": "AggregateHavingItemOnExchangeLimit",
"itemId": 176,
"stockId": 0,
"cardType": 0,
"officeLv": 0,
"officeProductId": 0,
"isAscendingOrder": true,
"relationProductIds": []
}
]
},
{
"productId": 221843,
"storeId": 63,
"sortWeight": 1000,
"exchangeLimit": 1,
"startAt": null,
"endAt": "2024-06-06 14:00:00",
"resetType": 0,
"resetDetail": null,
"product": {
"rewardType": 3,
"objectId": 79,
"objectValue": 5
},
"currency": {
"currencyType": 3,
"objectId": 172,
"objectValue": 2500
},
"condition": []
},
{
"productId": 221844,
"storeId": 63,
"sortWeight": 1000,
"exchangeLimit": 20,
"startAt": null,
"endAt": "2024-06-06 14:00:00",
"resetType": 0,
"resetDetail": null,
"product": {
"rewardType": 3,
"objectId": 78,
"objectValue": 5
},
"currency": {
"currencyType": 3,
"objectId": 172,
"objectValue": 65
},
"condition": []
},
{
"productId": 221845,
"storeId": 63,
"sortWeight": 1000,
"exchangeLimit": 15,
"startAt": null,
"endAt": "2024-06-06 14:00:00",
"resetType": 0,
"resetDetail": null,
"product": {
"rewardType": 3,
"objectId": 59,
"objectValue": 10
},
"currency": {
"currencyType": 3,
"objectId": 172,
"objectValue": 1000
},
"condition": []
},
{
"productId": 221846,
"storeId": 63,
"sortWeight": 1000,
"exchangeLimit": 350,
"startAt": null,
"endAt": "2024-06-06 14:00:00",
"resetType": 0,
"resetDetail": null,
"product": {
"rewardType": 3,
"objectId": 11,
"objectValue": 1000
},
"currency": {
"currencyType": 3,
"objectId": 172,
"objectValue": 40
},
"condition": []
},
{
"productId": 221847,
"storeId": 63,
"sortWeight": 1000,
"exchangeLimit": 250,
"startAt": null,
"endAt": "2024-06-06 14:00:00",
"resetType": 0,
"resetDetail": null,
"product": {
"rewardType": 3,
"objectId": 30,
"objectValue": 1000
},
"currency": {
"currencyType": 3,
"objectId": 172,
"objectValue": 40
},
"condition": []
},
{
"productId": 221848,
"storeId": 63,
"sortWeight": 1000,
"exchangeLimit": 400,
"startAt": null,
"endAt": "2024-06-06 14:00:00",
"resetType": 0,
"resetDetail": null,
"product": {
"rewardType": 3,
"objectId": 35,
"objectValue": 500
},
"currency": {
"currencyType": 3,
"objectId": 172,
"objectValue": 20
},
"condition": []
},
{
"productId": 221849,
"storeId": 63,
"sortWeight": 1000,
"exchangeLimit": 30,
"startAt": null,
"endAt": "2024-06-06 14:00:00",
"resetType": 0,
"resetDetail": null,
"product": {
"rewardType": 3,
"objectId": 12,
"objectValue": 1
},
"currency": {
"currencyType": 3,
"objectId": 172,
"objectValue": 40
},
"condition": []
},
{
"productId": 221850,
"storeId": 63,
"sortWeight": 1000,
"exchangeLimit": 15,
"startAt": null,
"endAt": "2024-06-06 14:00:00",
"resetType": 0,
"resetDetail": null,
"product": {
"rewardType": 3,
"objectId": 13,
"objectValue": 1
},
"currency": {
"currencyType": 3,
"objectId": 172,
"objectValue": 80
},
"condition": []
},
{
"productId": 221851,
"storeId": 63,
"sortWeight": 1000,
"exchangeLimit": 5,
"startAt": null,
"endAt": "2024-06-06 14:00:00",
"resetType": 0,
"resetDetail": null,
"product": {
"rewardType": 3,
"objectId": 14,
"objectValue": 1
},
"currency": {
"currencyType": 3,
"objectId": 172,
"objectValue": 160
},
"condition": []
},
{
"productId": 221852,
"storeId": 63,
"sortWeight": 1000,
"exchangeLimit": 60,
"startAt": null,
"endAt": "2024-06-06 14:00:00",
"resetType": 0,
"resetDetail": null,
"product": {
"rewardType": 3,
"objectId": 24,
"objectValue": 1
},
"currency": {
"currencyType": 3,
"objectId": 172,
"objectValue": 40
},
"condition": []
},
{
"productId": 221853,
"storeId": 63,
"sortWeight": 1000,
"exchangeLimit": 30,
"startAt": null,
"endAt": "2024-06-06 14:00:00",
"resetType": 0,
"resetDetail": null,
"product": {
"rewardType": 3,
"objectId": 25,
"objectValue": 1
},
"currency": {
"currencyType": 3,
"objectId": 172,
"objectValue": 80
},
"condition": []
},
{
"productId": 221854,
"storeId": 63,
"sortWeight": 1000,
"exchangeLimit": 10,
"startAt": null,
"endAt": "2024-06-06 14:00:00",
"resetType": 0,
"resetDetail": null,
"product": {
"rewardType": 3,
"objectId": 26,
"objectValue": 1
},
"currency": {
"currencyType": 3,
"objectId": 172,
"objectValue": 160
},
"condition": []
},
{
"productId": 221855,
"storeId": 63,
"sortWeight": 1000,
"exchangeLimit": 40,
"startAt": null,
"endAt": "2024-06-06 14:00:00",
"resetType": 0,
"resetDetail": null,
"product": {
"rewardType": 3,
"objectId": 53,
"objectValue": 1
},
"currency": {
"currencyType": 3,
"objectId": 172,
"objectValue": 100
},
"condition": []
},
{
"productId": 221856,
"storeId": 63,
"sortWeight": 1000,
"exchangeLimit": 0,
"startAt": null,
"endAt": "2024-06-06 14:00:00",
"resetType": 0,
"resetDetail": null,
"product": {
"rewardType": 3,
"objectId": 35,
"objectValue": 5
},
"currency": {
"currencyType": 3,
"objectId": 172,
"objectValue": 1
},
"condition": []
}
],
"characters": []
}