{
"storeId": 8,
"storeName": "キャンペーンアイテム交換所",
"storeBanner": "",
"sortWeight": 1100,
"startAt": null,
"endAt": "2021-04-16 18:00:00",
"products": [
{
"productId": 220242,
"storeId": 8,
"exchangeLimit": 1,
"startAt": null,
"endAt": null,
"resetType": 0,
"resetDetail": null,
"product": {
"rewardType": 1,
"objectId": 104511,
"objectValue": 1
},
"currency": {
"currencyType": 3,
"objectId": 52,
"objectValue": 200
},
"condition": []
},
{
"productId": 220243,
"storeId": 8,
"exchangeLimit": 1,
"startAt": null,
"endAt": null,
"resetType": 0,
"resetDetail": null,
"product": {
"rewardType": 2,
"objectId": 104511,
"objectValue": 1
},
"currency": {
"currencyType": 3,
"objectId": 52,
"objectValue": 200
},
"condition": []
},
{
"productId": 220244,
"storeId": 8,
"exchangeLimit": 5,
"startAt": null,
"endAt": null,
"resetType": 0,
"resetDetail": null,
"product": {
"rewardType": 3,
"objectId": 53,
"objectValue": 1
},
"currency": {
"currencyType": 3,
"objectId": 52,
"objectValue": 50
},
"condition": []
},
{
"productId": 220245,
"storeId": 8,
"exchangeLimit": 10,
"startAt": null,
"endAt": null,
"resetType": 0,
"resetDetail": null,
"product": {
"rewardType": 3,
"objectId": 53,
"objectValue": 1
},
"currency": {
"currencyType": 3,
"objectId": 52,
"objectValue": 100
},
"condition": []
},
{
"productId": 220246,
"storeId": 8,
"exchangeLimit": 20,
"startAt": null,
"endAt": null,
"resetType": 0,
"resetDetail": null,
"product": {
"rewardType": 3,
"objectId": 53,
"objectValue": 1
},
"currency": {
"currencyType": 3,
"objectId": 52,
"objectValue": 200
},
"condition": []
},
{
"productId": 220247,
"storeId": 8,
"exchangeLimit": 1000,
"startAt": null,
"endAt": null,
"resetType": 0,
"resetDetail": null,
"product": {
"rewardType": 3,
"objectId": 110451,
"objectValue": 1
},
"currency": {
"currencyType": 3,
"objectId": 52,
"objectValue": 5
},
"condition": []
},
{
"productId": 220248,
"storeId": 8,
"exchangeLimit": 2,
"startAt": null,
"endAt": null,
"resetType": 0,
"resetDetail": null,
"product": {
"rewardType": 3,
"objectId": 210451,
"objectValue": 1
},
"currency": {
"currencyType": 3,
"objectId": 52,
"objectValue": 350
},
"condition": []
},
{
"productId": 220249,
"storeId": 8,
"exchangeLimit": 2,
"startAt": null,
"endAt": null,
"resetType": 0,
"resetDetail": null,
"product": {
"rewardType": 3,
"objectId": 210451,
"objectValue": 1
},
"currency": {
"currencyType": 3,
"objectId": 52,
"objectValue": 700
},
"condition": []
},
{
"productId": 220250,
"storeId": 8,
"exchangeLimit": 1,
"startAt": null,
"endAt": null,
"resetType": 0,
"resetDetail": null,
"product": {
"rewardType": 3,
"objectId": 210451,
"objectValue": 1
},
"currency": {
"currencyType": 3,
"objectId": 52,
"objectValue": 1400
},
"condition": []
},
{
"productId": 220251,
"storeId": 8,
"exchangeLimit": 20,
"startAt": null,
"endAt": null,
"resetType": 0,
"resetDetail": null,
"product": {
"rewardType": 3,
"objectId": 24,
"objectValue": 1
},
"currency": {
"currencyType": 3,
"objectId": 52,
"objectValue": 60
},
"condition": []
},
{
"productId": 220252,
"storeId": 8,
"exchangeLimit": 0,
"startAt": null,
"endAt": null,
"resetType": 0,
"resetDetail": null,
"product": {
"rewardType": 3,
"objectId": 35,
"objectValue": 5
},
"currency": {
"currencyType": 3,
"objectId": 52,
"objectValue": 1
},
"condition": []
}
],
"characters": []
}